cli.py
gedcom_ajry.py
gedcom_benji.py
GEDCOM_AJRY-1.0.0.dist-info/LICENSE
GEDCOM_AJRY-1.0.0.dist-info/METADATA
GEDCOM_AJRY-1.0.0.dist-info/WHEEL
GEDCOM_AJRY-1.0.0.dist-info/entry_points.txt
GEDCOM_AJRY-1.0.0.dist-info/top_level.txt
GEDCOM_AJRY-1.0.0.dist-info/RECORD
