Metadata-Version: 2.1
Name: GEDCOM-AJRY
Version: 1.0.0
Summary: Course project of SSW555. Sprint_1 base line version.
Home-page: https://github.com/BenjiTheC/SSW555
Author: Benjamin; Ray; John; Javer
Author-email: ycai11@stevens.edu
License: UNKNOWN
Keywords: Stevens_Institute_of_Technology SSW555 CS555
Platform: UNKNOWN
Classifier: License :: OSI Approved :: MIT License
Classifier: Programming Language :: Python :: 3
Classifier: Programming Language :: Python :: 3.7
Requires-Dist: Click
Requires-Dist: tabulate
